Metadata-Version: 2.1
Name: notionshell
Version: 0.5
Summary: Partial notion commad line. Introduction to api, using official library.
Home-page: UNKNOWN
Author: TalWrii
Author-email: talwrii@gmail.com
License: BSD
Platform: UNKNOWN
